FaceAnalyzer/Face.py
FaceAnalyzer/FaceAnalyzer.py
FaceAnalyzer/Helpers.py
FaceAnalyzer/__init__.py
FaceAnalyzer/helpers/__init__.py
FaceAnalyzer/helpers/calibration/__init__.py
FaceAnalyzer/helpers/calibration/calibrate_camera.py
FaceAnalyzer/helpers/estimation/__init__.py
FaceAnalyzer/helpers/estimation/kalman.py
FaceAnalyzer/helpers/geometry/__init__.py
FaceAnalyzer/helpers/geometry/euclidian.py
FaceAnalyzer/helpers/geometry/orientation.py
FaceAnalyzer/helpers/ui/__init__.py
FaceAnalyzer/helpers/ui/opencv/__init__.py
FaceAnalyzer/helpers/ui/pillow/__init__.py
FaceAnalyzer/helpers/ui/pygame/__init__.py
FaceAnalyzer/helpers/ui/pygame/colors.py
FaceAnalyzer/helpers/ui/sqtui/__init__.py
FaceAnalyzer-0.1.33.dist-info/LICENSE
FaceAnalyzer-0.1.33.dist-info/METADATA
FaceAnalyzer-0.1.33.dist-info/WHEEL
FaceAnalyzer-0.1.33.dist-info/top_level.txt
FaceAnalyzer-0.1.33.dist-info/RECORD
