Metadata-Version: 2.1
Name: FaceAnalyzer
Version: 0.1.33
Summary: A python library for face detection and features extraction based on mediapipe library
Home-page: https://github.com/ParisNeo/FaceAnalyzer
Author: Saifeddine ALOUI
Author-email: aloui.saifeddine@gmail.com
License: UNKNOWN
Platform: UNKNOWN
Classifier: Programming Language :: Python :: 3.8
Classifier: License :: OSI Approved :: MIT License
Classifier: Operating System :: OS Independent
License-File: LICENSE
Requires-Dist: numpy
Requires-Dist: mediapipe
Requires-Dist: scipy
Requires-Dist: opencv-python
Requires-Dist: Pillow
Requires-Dist: cssutils
Requires-Dist: sqtui
Requires-Dist: pygame
Requires-Dist: OOPyGame
Requires-Dist: tqdm
Provides-Extra: dev
